{
 "absolute_value": 0,
 "align_labels_right": 0,
 "creation": "2023-06-15 00:55:37.223609",
 "css": "",
 "custom_format": 1,
 "default_print_language": "en",
 "disabled": 0,
 "doc_type": "Item",
 "docstatus": 0,
 "doctype": "Print Format",
 "font_size": 14,
 "html": "<style>\r\n    body {\r\n        margin: 0;\r\n        padding: 0;\r\n        -webkit-touch-callout: none;\r\n        -webkit-user-select: none;\r\n        -khtml-user-select: none;\r\n        -moz-user-select: none;\r\n        -ms-user-select: none;\r\n        user-select: none;\r\n    }\r\n    .main {\r\n        border: 1px solid rgb(209, 207, 207);\r\n        width: 1.5in;\r\n        height: 1in;\r\n        position: fixed;\r\n        margin: 0 auto;\r\n        right: 0;\r\n        left: 0;\r\n        display: flex;\r\n        flex-direction: column;\r\n        justify-content: space-between;\r\n    }\r\n    .print-format p {\r\n    margin: 0px 0px 0px;\r\n}\r\n    .barcode_header {\r\n        width: 50mm;\r\n        height: 3mm;\r\n        padding-top: 1mm !important;\r\n        padding: 0mm;\r\n        align-items: center;\r\n        margin: 0;\r\n        display: flex;\r\n        padding-left: 1mm;\r\n        font-size: 9px;\r\n    }\r\n    .item_details {\r\n        height: 7mm;\r\n        min-height: 7mm;\r\n        align-items: center;\r\n        display: flex;\r\n        padding-left: 1mm;\r\n        padding-bottom: 4mm;\r\n        justify-content: space-between;\r\n    }\r\n    .item_code {\r\n        font-size: 10px;\r\n        text-align: left;\r\n    }\r\n    .item_price {\r\n        font-size: 9px;\r\n        font-weight: 600;\r\n        text-align: right;\r\n        white-space: nowrap;\r\n    }\r\n    .item_name {\r\n        font-size: 7px;\r\n        font-weight: 600;\r\n        text-align: left;\r\n        padding-left: 2mm;\r\n        white-space: normal;\r\n        height: unset;\r\n        margin-top: 1mm;\r\n    }\r\n    .item_barcode_number {\r\n        font-size: 7px;\r\n        font-weight: 600;\r\n        text-align: center;\r\n        padding-left: 2mm;\r\n        white-space: nowrap;\r\n        margin-bottom: 1mm;\r\n    }\r\n    .item_barcode {\r\n        width: 50mm;\r\n        height: 11mm;\r\n        margin-bottom: 1mm;\r\n    }\r\n    svg.barcode {\r\n        max-width: 50mm;\r\n        min-width: 35mm;\r\n        height: 12mm;\r\n        min-height: 12mm;\r\n        padding-left: 1mm;\r\n        padding-right: 1mm;\r\n        margin: 0 auto;\r\n        right: 0;\r\n        left: 0;\r\n    }\r\n    .print-format.print-format-preview {\r\n        width: 25mm;\r\n        height: 12mm;\r\n        display: contents;\r\n        position: relative;\r\n    }\r\n    @media print {\r\n        .main {\r\n            border: none !important;\r\n        }\r\n    } \r\n</style>\r\n\r\n<!-- ====================== Barcode ============================== -->\r\n<div class=\"main\">\r\n    <div class=\"barcode_header\">\r\n        <p class=\"\">Qetah Trading and Tailoring</p>\r\n    </div>\r\n    <div class=\"item_name\">\r\n        <p class=\"\">{{ doc.item_code }}</p>\r\n    </div>\r\n    <div class=\"item_barcode\">\r\n        {% set uom = \"Offer\" %}\r\n        {% for barcode in doc.barcodes %}\r\n            {% if barcode.uom == uom %}\r\n                <svg class=\"barcode\" jsbarcode-format=\"CODE128\" jsbarcode-value=\"{{ barcode.barcode }}\" jsbarcode-height=\"50\"\r\n                     jsbarcode-width=\"2\" jsbarcode-fontsize=\"0\" jsbarcode-textmargin=\"1\" jsbarcode-margin=\"0\" jsbarcode-fontoptions=\"bold\">\r\n                </svg>\r\n    </div>\r\n    <div class=\"item_barcode_number\">\r\n        <p class=\"\">{{ barcode.barcode }}</p>\r\n    </div>\r\n    <div class=\"item_details\">\r\n        <table>\r\n            <tbody>\r\n                <tr>\r\n                    <td>\r\n                        {% set price = frappe.db.get_value(\"Item Price\", {\"item_code\": doc.name, \"selling\": 1, \"uom\": uom}, \"price_list_rate\") or frappe.db.get_value(\"Item Price\", {\"item_code\": doc.variant_of, \"uom\": uom}, \"price_list_rate\") or 0 %}\r\n                        <p class=\"item_price\">Price {{ price }} QR/{{ uom }}</p>\r\n                                    {% endif %}\r\n        {% endfor %}\r\n                    </td>\r\n                </tr>\r\n            </tbody>\r\n        </table>\r\n    </div>\r\n</div>\r\n\r\n<script src=\"https://cdn.jsdelivr.net/npm/jsbarcode@3.11.0/dist/JsBarcode.all.min.js\"></script>\r\n<script>\r\n\r\nJsBarcode(\".barcode\").init();\r\n</script>\r\n\r\n<!-- ====================== ../Barcode ============================== -->",
 "idx": 0,
 "line_breaks": 0,
 "margin_bottom": 15.0,
 "margin_left": 15.0,
 "margin_right": 15.0,
 "margin_top": 15.0,
 "modified": "2024-06-03 09:48:58.724175",
 "modified_by": "malsaad@qetah.qa",
 "module": "Qetah",
 "name": "Barcode Offer",
 "owner": "malsaad@qetah.qa",
 "page_number": "Hide",
 "print_format_builder": 0,
 "print_format_builder_beta": 0,
 "print_format_type": "Jinja",
 "raw_printing": 0,
 "show_section_headings": 0,
 "standard": "Yes"
}